ovrlpy/__init__.py
ovrlpy/_kde.py
ovrlpy/_ovrlp.py
ovrlpy/_patching.py
ovrlpy/_plotting.py
ovrlpy/_subslicing.py
ovrlpy/_utils.py
ovrlpy/io.py
ovrlpy-1.0.1.dist-info/licenses/LICENSE
ovrlpy-1.0.1.dist-info/METADATA
ovrlpy-1.0.1.dist-info/WHEEL
ovrlpy-1.0.1.dist-info/top_level.txt
ovrlpy-1.0.1.dist-info/RECORD
