Metadata-Version: 2.4
Name: ovrlpy
Version: 1.0.1
Summary: A python tool to investigate cell overlaps in imaging-based spatial transcriptomics data.
Author-email: Sebastian Tiesmeyer <sebastian.tiesmeyer@bih-charite.de>, Nikla Müller-Bötticher <niklas.mueller-boetticher@bih-charite.de>
License: MIT License
Project-URL: Homepage, https://github.com/HiDiHlabs/ovrl.py
Project-URL: Documentation, https://ovrlpy.readthedocs.io
Project-URL: Repository, https://github.com/HiDiHlabs/ovrl.py
Project-URL: Issues, https://github.com/HiDiHlabs/ovrl.py/issues
Classifier: Intended Audience :: Science/Research
Classifier: License :: OSI Approved :: MIT License
Classifier: Operating System :: OS Independent
Classifier: Programming Language :: Python :: 3
Classifier: Topic :: Scientific/Engineering :: Bio-Informatics
Requires-Python: <3.14,>=3.11
License-File: LICENSE
Requires-Dist: anndata>=0.10
Requires-Dist: matplotlib~=3.8
Requires-Dist: matplotlib-scalebar
Requires-Dist: numpy<3,>=1.25
Requires-Dist: pandas~=2.0
Requires-Dist: polars[pandas]~=1.0
Requires-Dist: scikit-image>=0.18
Requires-Dist: scikit-learn~=1.4
Requires-Dist: scipy~=1.11
Requires-Dist: tqdm~=4.65
Requires-Dist: umap-learn~=0.5
Provides-Extra: docs
Requires-Dist: sphinx~=8.0; extra == "docs"
Requires-Dist: sphinx-autoapi~=3.1; extra == "docs"
Requires-Dist: sphinx-copybutton; extra == "docs"
Requires-Dist: sphinx-rtd-theme; extra == "docs"
Requires-Dist: myst-nb; extra == "docs"
Dynamic: license-file
